{
  "enum_bool_yes": "Ja",
  "enum_bool_no": "Nej",
  "enum_interval_last_24_hours": "Senaste dygnet",
  "enum_interval_2_to_4_days_ago": "För 2-4 dagar sedan",
  "enum_interval_5_to_14_days_ago": "För 5-14 dagar sedan",
  "enum_interval_15_or_more_days_ago": "För mer än 15 dagar sedan",
  "definition_pain_details_started": "Hur länge har du haft smärta/besvär?",
  "definition_pain_details_ingestion": "Svårt att äta och dricka?",
  "definition_pain_details_when_chewing": "Smärta vid tuggning eller hela tiden?",
  "definition_pain_details_affects_sleep": "Påverkar smärtan din sömn?",
  "definition_pain_details_description": "Hur skulle du beskriva smärtan/besvären?",
  "definition_pain_details_description_distinct": "Skarp, distinkt",
  "definition_pain_details_description_aching": "Ilande",
  "definition_pain_details_description_constant": "Molande, ihållande",
  "definition_pain_details_description_pulsing": "Pulserande",
  "categories": "Vad kan vi hjälpa dig med?",
  "category_aching": "Tandvärk",
  "category_trauma": "Trauma (slag) mot tänder och käkar",
  "category_trauma_warning": "# Uppsök fysisk tandvård/sjukvård vid\n\n- Utslagna tänder\n\n- Blödande och öppna sår eller spruckna läppar\n\n- Kräkning och eventuell huvudvärk\n",
  "category_trauma_bleeding": "Blödning?",
  "category_trauma_pain": "Smärta?",
  "category_trauma_swelling": "Svullnad?",
  "category_trauma_when": "När (hände det)?",
  "category_trauma_where": "Var (sitter skadan)?",
  "category_trauma_how": "Hur skedde skadan (beskriv händelsen)?",
  "category_gums_and_mucosa": "Besvär från tandkött/slemhinna",
  "category_gums_and_mucosa_types": "Beskriv ditt besvär med tandkött/slemhinna",
  "category_gums_and_mucosa_types_bleeding": "Blödande tandkött",
  "category_gums_and_mucosa_types_swelling": "Svullnad i tandköttet",
  "category_gums_and_mucosa_types_mouth_ulcers": "Munsår",
  "category_gums_and_mucosa_types_blisters": "Blåsa/blåsor",
  "category_gums_and_mucosa_types_other": "Annat",
  "category_gums_and_mucosa_other": "Beskriv ditt besvär",
  "category_wisdom_teeth": "Problem med visdomstand/-tänder",
  "category_wisdom_teeth_swelling": "Svullet?",
  "category_wisdom_teeth_pain": "Smärta?",
  "category_wisdom_teeth_other": "Beskriv ditt besvär",
  "category_lost_restorative_crown_bridge": "Tappad lagning/lossad krona/bro",
  "category_lost_restorative_crown_bridge_when": "När tappade du lagningen?",
  "category_lost_restorative_crown_bridge_how": "Hur tappade du lagningen?",
  "category_lost_restorative_crown_bridge_sharp_cheek_tongue": "Är det vasst mot tungan eller kinden?",
  "category_lost_restorative_crown_bridge_pain": "Har du ont?",
  "category_lost_restorative_crown_bridge_other": "Beskriv ditt besvär",
  "category_jaws": "Problem med käkar (med eller utan huvudvärk)",
  "category_jaws_temple_face_jaw_temporomandibular": "Gör det ont i tinning, ansikte, käke eller käkled en gång i veckan eller oftare?",
  "category_jaws_gape_chewing": "Gör det ont när du gapar eller tuggar, en gång i veckan eller oftare?",
  "category_jaws_locked_snags": "Har du låsningar eller upphakningar i käken en gång i veckan eller oftare?",
  "category_jaws_gape_chewing_other": "Beskriv ditt besvär",
  "category_sensitivity": "Besvär med ilningar",
  "category_sensitivity_started": "När uppkom besväret?",
  "category_sensitivity_when": "När uppstår dina ilningar?",
  "category_cosmetic": "Frågor om tändernas utseende/estetisk tandvård",
  "category_cosmetic_types_crooked_teeth": "Sneda tänder",
  "category_cosmetic_types_sparse_teeth": "Glesa tänder",
  "category_cosmetic_types_color": "Tändernas färg",
  "category_cosmetic_types_short_worn": "Slitna/korta tänder",
  "category_cosmetic_types_missing_teeth": "En eller flera tänder saknas",
  "category_cosmetic_other": "Annat besvär",
  "category_dental_fear": "Tandvårdsrädsla",
  "category_dental_fear_description": "# Lugnande text\n\nLägg in lugnande text (faktabaserad).",
  "category_dental_fear_what": "Beskriv kortfattat vad du vill prata om",
  "category_other": "Inget av ovanstående",
  "category_other_description": "Beskriv kortfattat vad du vill prata om"
}
